{"metadata": {"dbt_schema_version": "https://schemas.getdbt.com/dbt/catalog/v1.json", "dbt_version": "1.7.10", "generated_at": "2024-03-26T12:54:49.660955Z", "invocation_id": "f26b45ee-60f3-4f2d-ae41-a25ce9a4ab16", "env": {}}, "nodes": {"model.plateforme_data_demo.stg_infogreffe__chiffres_cles": {"metadata": {"type": "table", "schema": "1_stage_dbt", "name": "stg_infogreffe__chiffres_cles", "database": "plateforme-data-demo", "comment": null, "owner": null}, "columns": {"lb_fichier_source": {"type": "STRING", "index": 1, "name": "lb_fichier_source", "comment": null}, "lb_denomination": {"type": "STRING", "index": 2, "name": "lb_denomination", "comment": null}, "cd_siren": {"type": "STRING", "index": 3, "name": "cd_siren", "comment": null}, "cd_nic": {"type": "STRING", "index": 4, "name": "cd_nic", "comment": null}, "lb_forme_juridique": {"type": "STRING", "index": 5, "name": "lb_forme_juridique", "comment": null}, "cd_ape": {"type": "STRING", "index": 6, "name": "cd_ape", "comment": null}, "lb_ape": {"type": "STRING", "index": 7, "name": "lb_ape", "comment": null}, "lb_adresse": {"type": "STRING", "index": 8, "name": "lb_adresse", "comment": null}, "cd_postal": {"type": "STRING", "index": 9, "name": "cd_postal", "comment": null}, "lb_ville": {"type": "STRING", "index": 10, "name": "lb_ville", "comment": null}, "cd_departement": {"type": "STRING", "index": 11, "name": "cd_departement", "comment": null}, "lb_departement": {"type": "STRING", "index": 12, "name": "lb_departement", "comment": null}, "lb_region": {"type": "STRING", "index": 13, "name": "lb_region", "comment": null}, "cd_greffe": {"type": "STRING", "index": 14, "name": "cd_greffe", "comment": null}, "lb_greffe": {"type": "STRING", "index": 15, "name": "lb_greffe", "comment": null}, "dt_immatriculation": {"type": "DATE", "index": 16, "name": "dt_immatriculation", "comment": null}, "dt_radiation": {"type": "DATE", "index": 17, "name": "dt_radiation", "comment": null}, "lb_statut": {"type": "STRING", "index": 18, "name": "lb_statut", "comment": null}, "cd_geolocalisation": {"type": "STRING", "index": 19, "name": "cd_geolocalisation", "comment": null}, "dt_publication": {"type": "DATE", "index": 20, "name": "dt_publication", "comment": null}, "cd_id": {"type": "STRING", "index": 21, "name": "cd_id", "comment": null}, "lb_fiche_identite": {"type": "STRING", "index": 22, "name": "lb_fiche_identite", "comment": null}, "cd_annee": {"type": "STRING", "index": 23, "name": "cd_annee", "comment": null}, "dt_cloture_exercice": {"type": "DATE", "index": 24, "name": "dt_cloture_exercice", "comment": null}, "nb_mois_periode": {"type": "INT64", "index": 25, "name": "nb_mois_periode", "comment": null}, "mt_ca": {"type": "NUMERIC", "index": 26, "name": "mt_ca", "comment": null}, "mt_resultat": {"type": "NUMERIC", "index": 27, "name": "mt_resultat", "comment": null}, "lb_effectif": {"type": "STRING", "index": 28, "name": "lb_effectif", "comment": null}, "lb_tranche_ca_millesime": {"type": "STRING", "index": 29, "name": "lb_tranche_ca_millesime", "comment": null}}, "stats": {"num_rows": {"id": "num_rows", "label": "# Rows", "value": 5771757, "include": true, "description": "Approximate count of rows in this table"}, "num_bytes": {"id": "num_bytes", "label": "Approximate Size", "value": 2395010316, "include": true, "description": "Approximate size of table as reported by BigQuery"}, "has_stats": {"id": "has_stats", "label": "Has Stats?", "value": true, "include": false, "description": "Indicates whether there are statistics for this table"}}, "unique_id": "model.plateforme_data_demo.stg_infogreffe__chiffres_cles"}}, "sources": {"source.plateforme_data_demo.infogreffe.chiffres_cles": {"metadata": {"type": "external", "schema": "0_raw_infogreffe", "name": "chiffres_cles", "database": "plateforme-data-demo", "comment": null, "owner": null}, "columns": {"denomination": {"type": "STRING", "index": 1, "name": "denomination", "comment": null}, "siren": {"type": "STRING", "index": 2, "name": "siren", "comment": null}, "nic": {"type": "STRING", "index": 3, "name": "nic", "comment": null}, "forme_juridique": {"type": "STRING", "index": 4, "name": "forme_juridique", "comment": null}, "code_ape": {"type": "STRING", "index": 5, "name": "code_ape", "comment": null}, "libelle_ape": {"type": "STRING", "index": 6, "name": "libelle_ape", "comment": null}, "adresse": {"type": "STRING", "index": 7, "name": "adresse", "comment": null}, "code_postal": {"type": "STRING", "index": 8, "name": "code_postal", "comment": null}, "ville": {"type": "STRING", "index": 9, "name": "ville", "comment": null}, "num_dept": {"type": "STRING", "index": 10, "name": "num_dept", "comment": null}, "departement": {"type": "STRING", "index": 11, "name": "departement", "comment": null}, "region": {"type": "STRING", "index": 12, "name": "region", "comment": null}, "code_greffe": {"type": "STRING", "index": 13, "name": "code_greffe", "comment": null}, "greffe": {"type": "STRING", "index": 14, "name": "greffe", "comment": null}, "date_immatriculation": {"type": "STRING", "index": 15, "name": "date_immatriculation", "comment": null}, "date_radiation": {"type": "STRING", "index": 16, "name": "date_radiation", "comment": null}, "statut": {"type": "STRING", "index": 17, "name": "statut", "comment": null}, "geolocalisation": {"type": "STRING", "index": 18, "name": "geolocalisation", "comment": null}, "date_de_publication": {"type": "STRING", "index": 19, "name": "date_de_publication", "comment": null}, "millesime_1": {"type": "STRING", "index": 20, "name": "millesime_1", "comment": null}, "date_de_cloture_exercice_1": {"type": "STRING", "index": 21, "name": "date_de_cloture_exercice_1", "comment": null}, "duree_1": {"type": "STRING", "index": 22, "name": "duree_1", "comment": null}, "ca_1": {"type": "STRING", "index": 23, "name": "ca_1", "comment": null}, "resultat_1": {"type": "STRING", "index": 24, "name": "resultat_1", "comment": null}, "effectif_1": {"type": "STRING", "index": 25, "name": "effectif_1", "comment": null}, "millesime_2": {"type": "STRING", "index": 26, "name": "millesime_2", "comment": null}, "date_de_cloture_exercice_2": {"type": "STRING", "index": 27, "name": "date_de_cloture_exercice_2", "comment": null}, "duree_2": {"type": "STRING", "index": 28, "name": "duree_2", "comment": null}, "ca_2": {"type": "STRING", "index": 29, "name": "ca_2", "comment": null}, "resultat_2": {"type": "STRING", "index": 30, "name": "resultat_2", "comment": null}, "effectif_2": {"type": "STRING", "index": 31, "name": "effectif_2", "comment": null}, "millesime_3": {"type": "STRING", "index": 32, "name": "millesime_3", "comment": null}, "date_de_cloture_exercice_3": {"type": "STRING", "index": 33, "name": "date_de_cloture_exercice_3", "comment": null}, "duree_3": {"type": "STRING", "index": 34, "name": "duree_3", "comment": null}, "ca_3": {"type": "STRING", "index": 35, "name": "ca_3", "comment": null}, "resultat_3": {"type": "STRING", "index": 36, "name": "resultat_3", "comment": null}, "effectif_3": {"type": "STRING", "index": 37, "name": "effectif_3", "comment": null}, "id": {"type": "STRING", "index": 38, "name": "id", "comment": null}, "fiche_identite": {"type": "STRING", "index": 39, "name": "fiche_identite", "comment": null}, "tranche_ca_millesime_1": {"type": "STRING", "index": 40, "name": "tranche_ca_millesime_1", "comment": null}, "tranche_ca_millesime_2": {"type": "STRING", "index": 41, "name": "tranche_ca_millesime_2", "comment": null}, "tranche_ca_millesime_3": {"type": "STRING", "index": 42, "name": "tranche_ca_millesime_3", "comment": null}}, "stats": {"has_stats": {"id": "has_stats", "label": "Has Stats?", "value": false, "include": false, "description": "Indicates whether there are statistics for this table"}}, "unique_id": "source.plateforme_data_demo.infogreffe.chiffres_cles"}}, "errors": null}